slim_helper-2.5.0.dist-info/METADATA
slim_helper-2.5.0.dist-info/WHEEL
slim_helper/__init__.py
slim_helper/common.py
slim_helper/database.py
slim_helper/display.py
slim_helper/io.py
slim_helper/process.py
slim_helper/security.py
slim_helper/task.py
slim_helper-2.5.0.dist-info/RECORD
