Metadata-Version: 2.1
Name: slim-helper
Version: 2.5.0
Summary: Default template for PDM package
License: MIT
Requires-Python: >=3.11
Provides-Extra: postgres
Provides-Extra: oracle
Provides-Extra: all
Requires-Dist: psycopg>=3.1.14; extra == "postgres"
Requires-Dist: oracledb>=1.4.2; extra == "oracle"
Requires-Dist: slim-helper[oracle,postgres]; extra == "all"
